funcwrap.py
funcwrap-0.0.1.dist-info/METADATA
funcwrap-0.0.1.dist-info/WHEEL
funcwrap-0.0.1.dist-info/top_level.txt
funcwrap-0.0.1.dist-info/zip-safe
funcwrap-0.0.1.dist-info/RECORD
