Metadata-Version: 2.1
Name: funcwrap
Version: 0.0.1
Summary: Helps function wrappers/decorators with perfect forwarding
Home-page: https://github.com/coldfix/funcwrap
Author: Thomas Gläßle
Author-email: thomas@coldfix.de
License: Unlicense
Platform: UNKNOWN
Classifier: Development Status :: 4 - Beta
Classifier: Intended Audience :: Developers
Classifier: Operating System :: OS Independent
Classifier: Programming Language :: Python :: 3
Classifier: Topic :: Software Development
Classifier: License :: Public Domain
Requires-Python: >=3.5
